arsmachina/__init__.py
arsmachina-0.1.0.dist-info/LICENSE
arsmachina-0.1.0.dist-info/METADATA
arsmachina-0.1.0.dist-info/WHEEL
arsmachina-0.1.0.dist-info/RECORD
