Metadata-Version: 2.3
Name: arsmachina
Version: 0.1.0
Summary: 
Author: Suhail
Author-email: suhailece@gmail.com
Requires-Python: >=3.12,<4.0
Classifier: Programming Language :: Python :: 3
Classifier: Programming Language :: Python :: 3.12
Classifier: Programming Language :: Python :: 3.13
